{
  "checkedAt": "2026-06-28T12:45:20.190Z",
  "changedCount": 1,
  "errorCount": 0,
  "schools": [
    {
      "name": "Trinity School admissions/events",
      "url": "https://www.trinityschoolnyc.org/admissions/admissions-k-4",
      "status": "unchanged",
      "checkedAt": "2026-06-28T12:45:20.190Z",
      "httpStatus": 200,
      "hash": "3958718345e2d0dba1d1029e1549e092d89f0e68d00125a13e8e9e91e32af3a1",
      "previousHash": "3958718345e2d0dba1d1029e1549e092d89f0e68d00125a13e8e9e91e32af3a1",
      "hints": [
        "Check: Applicants to Kindergarten must turn five years old by September 1st of the year they enter Kindergarten.",
        "Check: The application for the 2026-2027 school year is now closed.",
        "Check: Information regarding the application process and key dates for the 2027-2028 school year will be available in June 2026.",
        "Check: While we do not offer spring tours, we will offer a Spring Virtual Information Session on Friday, May 1st at 9:00 a.m.",
        "Check: for those families interested in applying to Kindergarten for the 2027-2028 school year.",
        "Check: This webinar will provide information about Trinity’s admissions process, program, and community.",
        "Check: Please note: Attendance is entirely optional and the webinar will be recorded for those families who are not able to join virtually.",
        "Check: Please click here to join the webinar."
      ]
    },
    {
      "name": "The Dalton School admissions",
      "url": "https://www.dalton.org/apply/steps-to-apply",
      "status": "unchanged",
      "checkedAt": "2026-06-28T12:45:20.190Z",
      "httpStatus": 200,
      "hash": "e62b665d5a7a41842700d5fb3c46d64c1a5e8456f7fe4d48b02de007274dcf4f",
      "previousHash": "e62b665d5a7a41842700d5fb3c46d64c1a5e8456f7fe4d48b02de007274dcf4f",
      "hints": [
        "Check: Within the First Program, the primary entry grade is Kindergarten.",
        "Check: In order to apply to Kindergarten, all children must be 5 years old by September 1 of the year they enter Kindergarten.",
        "Check: Students born in June, July, or August should consult with their early childhood directors about the student’s readiness to apply.",
        "Check: Dalton adheres strictly to a May 31 deadline for children with summer birthdays.",
        "Check: Kindergarten applications open on August 13 and will be accepted until 12:00 PM on November 13.",
        "Check: Enrollment notifications will be posted on Ravenna in February, per the ISAAGNY timetable .",
        "Check: School Application Through Ravenna.",
        "Check: The application is available in Ravenna after 12:00 PM on August 13 and due no later than noon on November 13."
      ]
    },
    {
      "name": "Collegiate School admissions",
      "url": "https://www.collegiateschool.org/admissions/apply-to-kindergarten",
      "status": "unchanged",
      "checkedAt": "2026-06-28T12:45:20.190Z",
      "httpStatus": 200,
      "hash": "c2425d6741f1f7695415a144cc78e665fa54d8f02402a7c63ceba66809b6f184",
      "previousHash": "c2425d6741f1f7695415a144cc78e665fa54d8f02402a7c63ceba66809b6f184",
      "hints": [
        "Check: Virtual Tour (opens in new window/tab).",
        "Check: Please see below the steps required for completing your application.",
        "Check: Applicants to Kindergarten can begin the application process immediately.",
        "Check: Step 1 – Submit Your Application, Optional Photo, and Applicant’s Work Sample.",
        "Check: Step 3 – Required Parent Interview, Required Applicant Visit, and Optional Parent Tour.",
        "Check: Please submit your application, optional photo, and child's work sample by November 14, 2025, and keep a copy for your files.",
        "Check: Please request your current school to fill out the Collegiate Confidential Report Form For Kindergarten and have them submit it directly to our Admissions Office by January 5, 2026.",
        "Check: Schools may also submit the ISAAGNY Confidential School Report if they prefer."
      ]
    },
    {
      "name": "The Allen-Stevenson School admissions",
      "url": "https://www.allen-stevenson.org/admissions/apply",
      "status": "unchanged",
      "checkedAt": "2026-06-28T12:45:20.190Z",
      "httpStatus": 200,
      "hash": "af00b35edd659447249f9fbb49e9d544969b24f9a08deb49f4deb6427b438d2e",
      "previousHash": "af00b35edd659447249f9fbb49e9d544969b24f9a08deb49f4deb6427b438d2e",
      "hints": [
        "Check: Admissions Timeline for 2027-2028 Applicants.",
        "Check: Applications Due: December 1, 2026.",
        "Check: ISAAGNY Early Notification for Sibling & Legacy qualifying applicants: December 9, 2026.",
        "Check: ISAAGNY Notification for Kindergarten: February 4, 2027.",
        "Check: ISAAGNY Notification for Grades 1-8: February 10, 2027.",
        "Check: 2027-2028 School Year Applications.",
        "Check: Applications for the 2027-2028 school year open on August 27, 2026.",
        "Check: Are seasonal tours available for prospective parents?."
      ]
    },
    {
      "name": "The Allen-Stevenson School visits/events",
      "url": "https://www.allen-stevenson.org/admissions/visit-and-meet-us",
      "status": "changed",
      "checkedAt": "2026-06-28T12:45:20.190Z",
      "httpStatus": 200,
      "hash": "2dc4e780badb6720b55b2e44ac7267db57a027da49e09534f772a29679d14303",
      "previousHash": "de6f8cb9058a04da1da9c05665bfc27fd31219268128e0d845763152436c17bd",
      "hints": [
        "Check: Visit and Meet Us | The Allen Stevenson.",
        "Check: Applications for the 2027-2028 school year go live on August 27, 2026.",
        "Check: After submitting an application, prospective parents will have a parent-led tour of the School.",
        "Check: During the tour, you will have an opportunity to experience the life of the School and see our students in action."
      ]
    },
    {
      "name": "Trevor Day School admissions/events",
      "url": "https://www.trevor.org/admissions/apply-to-lower-school-ps-5",
      "status": "unchanged",
      "checkedAt": "2026-06-28T12:45:20.190Z",
      "httpStatus": 200,
      "hash": "aa56998f5260d4d58077236aca170895bd5f1b9c10de8187371c66ad8ee9b40a",
      "previousHash": "aa56998f5260d4d58077236aca170895bd5f1b9c10de8187371c66ad8ee9b40a",
      "hints": [
        "Check: For 95 years, Trevor Day School has offered an innovative independent school education in the heart of Manhattan.",
        "Check: Applicants for Entry in Fall 2027.",
        "Check: The application deadline for the 2026-2027 school year has passed.",
        "Check: Applications for the 2027-2028 school year will be available on Ravenna in mid to late August.",
        "Check: Our fall tours run from October to December on Thursdays at 9:00 am.",
        "Check: Sign-up will be available on Ravenna in late August.",
        "Check: Should you have questions about your Ravenna account, please contact Ravenna-help@communitybrands.com.",
        "Check: Application Opens for Threes–5th Grade Mid to late August."
      ]
    },
    {
      "name": "The Browning School admissions/events",
      "url": "https://browning.edu/admission",
      "status": "unchanged",
      "checkedAt": "2026-06-28T12:45:20.190Z",
      "httpStatus": 200,
      "hash": "fb00d31446f2e7edc301a89781e440a066312ca1aafd1f30773f9f340adf3483",
      "previousHash": "fb00d31446f2e7edc301a89781e440a066312ca1aafd1f30773f9f340adf3483",
      "hints": [
        "Check: Back Mission and Values Why Families Choose Browning Our Community News & Blogs Equitable Practices & Social Impact Civil Discourse \"Buzzwords\" Magazine.",
        "Check: Back Admission Apply Now KinderFirst Upper School Expansion Discover Events Tuition & Tuition Assistance Request Information.",
        "Check: Back Faculty, Student & Parent Login Canvas Login Directory Community Calendar Volunteer Opportunities.",
        "Check: A non-refundable application fee of $75 must accompany each application.",
        "Check: The tuition for the 2026-2027 academic year is $71,670.",
        "Check: Admission decisions are made independently of financial need.",
        "Check: WHAT IS THE DEADLINE FOR SUBMITTING AN APPLICATION AND SCHEDULING APPOINTMENTS?.",
        "Check: Applications for entry in 2027 will open on Monday, August 10, 2026."
      ]
    },
    {
      "name": "The Town School dates/events",
      "url": "https://www.thetownschool.org/admissions/important-dates-and-events",
      "status": "unchanged",
      "checkedAt": "2026-06-28T12:45:20.190Z",
      "httpStatus": 200,
      "hash": "7ff09d1d6e9fd6e8c48e52d8bfbe59dec542e2315e08b05f30fec0d014a19830",
      "previousHash": "7ff09d1d6e9fd6e8c48e52d8bfbe59dec542e2315e08b05f30fec0d014a19830",
      "hints": [
        "Check: Please join us for a virtual \"Get to Know the Town School\" session on May 14th from 4:00-5:00pm.",
        "Check: Interested in the 2027-28 school year?",
        "Check: If you are interested in the 2026-2027 school year, please contact our Admissions Office directly at admissions@townschool.org .",
        "Check: Important Admissions Dates for 2027-28.",
        "Check: Financial Aid Application Available.",
        "Check: Early Notification Reply Deadline.",
        "Check: Kindergarten Enrollment Contract Deadline.",
        "Check: Grades 1-8 Enrollment Contract Deadline."
      ]
    },
    {
      "name": "United Nations International School admissions",
      "url": "https://www.unis.org/admissions/apply",
      "status": "unchanged",
      "checkedAt": "2026-06-28T12:45:20.190Z",
      "httpStatus": 200,
      "hash": "4409f4283b812be7fd3ee373de8bb5641ac08f5a1bbb0757797283dc7dd3205a",
      "previousHash": "4409f4283b812be7fd3ee373de8bb5641ac08f5a1bbb0757797283dc7dd3205a",
      "hints": [
        "Check: Parents' Association By-Laws & Meeting Minutes.",
        "Check: 2026 IB Conference - IB Teacher Training.",
        "Check: The Admissions section has information about the application process, including deadlines, application requirements, and answers to frequently asked questions.",
        "Check: The Admissions Department is happy to answer any questions a family has about UNIS and our application process.",
        "Check: Applications for entry in September 2027 will be available on September 1.",
        "Check: If you are still interested in applying for entry in the academic year 2026-27, please contact the admissions office ( admissions@unis.org ), as we have a few spots available in some grades.",
        "Check: Application Procedures (PreK-4).",
        "Check: To begin the application process, create an account in Ravenna."
      ]
    },
    {
      "name": "Columbia Grammar & Preparatory School admissions",
      "url": "https://www.cgps.org/admissions/apply-and-dates",
      "status": "unchanged",
      "checkedAt": "2026-06-28T12:45:20.190Z",
      "httpStatus": 200,
      "hash": "02a99327e904564caa397be0b8b4c8ee43c43a8fdc7f944d4f974bf4a7b01cc0",
      "previousHash": "02a99327e904564caa397be0b8b4c8ee43c43a8fdc7f944d4f974bf4a7b01cc0",
      "hints": [
        "Check: Inquire, Apply & Important Dates - Columbia Grammar & Preparatory School CGPS By Division Grammar School.",
        "Check: Academics Grammar School Pre-K & K at CGPS.",
        "Check: CGPS By Division Grammar School.",
        "Check: Columbia Grammar & Preparatory School Founded 1764 | Pre-K-12.",
        "Check: The application for the 2027-2028 academic year will open in mid-August!.",
        "Check: Grammar School, Pre-K-5: Janet Barrett ( jbarrett@cgps.org ).",
        "Check: Please note: Pre-Kindergarten applicants must be four years old before September 1, and Kindergarten applicants must be five years old before September 1.",
        "Check: Please create an account with the CGPS application portal and check it regularly throughout the admissions season to view your checklist and manage your application."
      ]
    },
    {
      "name": "Columbia Grammar & Preparatory School",
      "url": "https://www.cgps.org/",
      "status": "unchanged",
      "checkedAt": "2026-06-28T12:45:20.190Z",
      "httpStatus": 200,
      "hash": "4fdfb9cff1913ea2530df96cb2bd38baaaee71c7751de001f6db49a34cdc8cae",
      "previousHash": "4fdfb9cff1913ea2530df96cb2bd38baaaee71c7751de001f6db49a34cdc8cae",
      "hints": [
        "Check: Columbia Grammar & Preparatory School, Pre-K–12 Private School in NYC CGPS By Division Grammar School.",
        "Check: Academics Grammar School Pre-K & K at CGPS.",
        "Check: CGPS By Division Grammar School.",
        "Check: Columbia Grammar & Preparatory School Founded 1764 | Pre-K-12.",
        "Check: Columbia Grammar & Preparatory School is living proof that children can achieve their highest ambitions while keeping their spirits intact.",
        "Check: The Grammar School meets each child where they are and helps them develop into the most fully realized version of themselves.",
        "Check: At Columbia Grammar & Preparatory School, we pride ourselves on providing an individual experience for our students so that they may pursue as many avenues of interest as possible.",
        "Check: “As an educator and the parent of four very different children, I have been amazed by how well CGPS has been a wonderful fit for all of them."
      ]
    },
    {
      "name": "Hunter College Campus Schools",
      "url": "https://www.hunterschools.org/",
      "status": "unchanged",
      "checkedAt": "2026-06-28T12:45:20.190Z",
      "httpStatus": 200,
      "hash": "7e61c4f964b73fe3abe37a6da9a6784ed4c19f3d47d33dd60fc826289d885789",
      "previousHash": "7e61c4f964b73fe3abe37a6da9a6784ed4c19f3d47d33dd60fc826289d885789",
      "hints": [
        "Check: Eligibility for Fall 2027 Entry.",
        "Check: 6/16/2026 NDI's 50th Anniversary.",
        "Check: Elementary School News Archive.",
        "Check: 6/25/2026 Honoring the HCHS Class of 2026.",
        "Check: \" data-long=\"\" data-date=\"6/22/2026\" data-author=\"\" data-detailurl=\"/page/news-detail?pk=1629777&fromId=238856\"> Sean K.",
        "Check: \" data-long=\"\" data-date=\"6/16/2026\" data-author=\"\" data-detailurl=\"/page/news-detail?pk=1629664&fromId=238856\"> A Celebration of Tradition, Talent, and Community at Hunter College High School.",
        "Check: \" data-title=\"Convocation 2026\">.",
        "Check: 6/16/2026 A Celebration of Tradition, Talent, and Community at Hunter College High School."
      ]
    },
    {
      "name": "NYC DOE Kindergarten",
      "url": "https://www.schools.nyc.gov/enrollment/enroll-grade-by-grade/kindergarten",
      "status": "unchanged",
      "checkedAt": "2026-06-28T12:45:20.190Z",
      "httpStatus": 200,
      "hash": "017d4c990f39c56aeaac304a70059d03056eef3d120bc6d984f2dbe6a12dc0f5",
      "previousHash": "017d4c990f39c56aeaac304a70059d03056eef3d120bc6d984f2dbe6a12dc0f5",
      "hints": [
        "Check: Assessments for Screened Schools.",
        "Check: Annual Parent Teacher Meetings for English Language Learners.",
        "Check: Bill of Rights for Parents of English Language Learners.",
        "Check: Extended School Year Services for July and August.",
        "Check: Genovesi Environmental Study Center.",
        "Check: Parents' Bill of Rights for Data Privacy and Security.",
        "Check: Gang Prevention and Intervention.",
        "Check: Food Service for Parents and Students."
      ]
    }
  ]
}
